README
setup.py
todoist_cli/__init__.py
todoist_cli/todoist_cli.py
todoist_cli.egg-info/PKG-INFO
todoist_cli.egg-info/SOURCES.txt
todoist_cli.egg-info/dependency_links.txt
todoist_cli.egg-info/entry_points.txt
todoist_cli.egg-info/requires.txt
todoist_cli.egg-info/top_level.txt