Metadata-Version: 1.0
Name: todoist-cli
Version: 0.0.1
Summary: A CLI for batch creating Todoist tasks.
Home-page: https://github.com/csu/todoist-cli
Author: Christopher Su
Author-email: gh@christopher.su
License: UNKNOWN
Platform: UNKNOWN
